MANIFEST.in
README.md
requirements.txt
setup.cfg
setup.py
dash_database/__init__.py
dash_database.egg-info/PKG-INFO
dash_database.egg-info/SOURCES.txt
dash_database.egg-info/dependency_links.txt
dash_database.egg-info/requires.txt
dash_database.egg-info/top_level.txt