Metadata-Version: 2.1
Name: dash-database
Version: 1.0
Summary: Manages user values for a dash app.
Home-page: https://github.com/ThibTrip/dash_database
Author: Thibault Bétrémieux
Author-email: thibault.betremieux@gmail.com
License: The Unlicense
Download-URL: https://github.com/ThibTrip/dash_database/archive/v1.tar.gz
Keywords: dash,plotly
Platform: UNKNOWN
Classifier: Development Status :: 5 - Production/Stable
Classifier: Programming Language :: Python :: 3
Classifier: Programming Language :: Python :: 3.6
Classifier: Programming Language :: Python :: 3.7
Classifier: License :: Public Domain
Classifier: Intended Audience :: Developers
Classifier: Operating System :: OS Independent
